[
  {
    "name" : "FontAwesome5FreeSolid",
    "hex" : "0xF000"
  },
  {
    "name" : "FontAwesome5FreeSolid",
    "hex" : "0xF001"
  },
  {
    "name" : "FontAwesome5FreeSolid",
    "hex" : "0xF002"
  },
  {
    "name" : "FontAwesome5FreeSolid",
    "hex" : "0xF004"
  },
  {
    "name" : "FontAwesome5FreeSolid",
    "hex" : "0xF005"
  },
  {
    "name" : "FontAwesome5FreeSolid",
    "hex" : "0xF007"
  },
  {
    "name" : "FontAwesome5FreeSolid",
    "hex" : "0xF008"
  },
  {
    "name" : "FontAwesome5FreeSolid",
    "hex" : "0xF009"
  },
  {
    "name" : "FontAwesome5FreeSolid",
    "hex" : "0xF00A"
  },
  {
    "name" : "FontAwesome5FreeSolid",
    "hex" : "0xF00B"
  },
  {
    "name" : "FontAwesome5FreeSolid",
    "hex" : "0xF00C"
  },
  {
    "name" : "FontAwesome5FreeSolid",
    "hex" : "0xF00D"
  },
  {
    "name" : "FontAwesome5FreeSolid",
    "hex" : "0xF00E"
  },
  {
    "name" : "FontAwesome5FreeSolid",
    "hex" : "0xF010"
  },
  {
    "name" : "FontAwesome5FreeSolid",
    "hex" : "0xF011"
  },
  {
    "name" : "FontAwesome5FreeSolid",
    "hex" : "0xF012"
  },
  {
    "name" : "FontAwesome5FreeSolid",
    "hex" : "0xF013"
  },
  {
    "name" : "FontAwesome5FreeSolid",
    "hex" : "0xF015"
  },
  {
    "name" : "FontAwesome5FreeSolid",
    "hex" : "0xF017"
  },
  {
    "name" : "FontAwesome5FreeSolid",
    "hex" : "0xF018"
  },
  {
    "name" : "FontAwesome5FreeSolid",
    "hex" : "0xF019"
  },
  {
    "name" : "FontAwesome5FreeSolid",
    "hex" : "0xF01C"
  },
  {
    "name" : "FontAwesome5FreeSolid",
    "hex" : "0xF01E"
  },
  {
    "name" : "FontAwesome5FreeSolid",
    "hex" : "0xF021"
  },
  {
    "name" : "FontAwesome5FreeSolid",
    "hex" : "0xF022"
  },
  {
    "name" : "FontAwesome5FreeSolid",
    "hex" : "0xF023"
  },
  {
    "name" : "FontAwesome5FreeSolid",
    "hex" : "0xF024"
  },
  {
    "name" : "FontAwesome5FreeSolid",
    "hex" : "0xF025"
  },
  {
    "name" : "FontAwesome5FreeSolid",
    "hex" : "0xF026"
  },
  {
    "name" : "FontAwesome5FreeSolid",
    "hex" : "0xF027"
  },
  {
    "name" : "FontAwesome5FreeSolid",
    "hex" : "0xF028"
  },
  {
    "name" : "FontAwesome5FreeSolid",
    "hex" : "0xF029"
  },
  {
    "name" : "FontAwesome5FreeSolid",
    "hex" : "0xF02A"
  },
  {
    "name" : "FontAwesome5FreeSolid",
    "hex" : "0xF02B"
  },
  {
    "name" : "FontAwesome5FreeSolid",
    "hex" : "0xF02C"
  },
  {
    "name" : "FontAwesome5FreeSolid",
    "hex" : "0xF02D"
  },
  {
    "name" : "FontAwesome5FreeSolid",
    "hex" : "0xF02E"
  },
  {
    "name" : "FontAwesome5FreeSolid",
    "hex" : "0xF02F"
  },
  {
    "name" : "FontAwesome5FreeSolid",
    "hex" : "0xF030"
  },
  {
    "name" : "FontAwesome5FreeSolid",
    "hex" : "0xF031"
  },
  {
    "name" : "FontAwesome5FreeSolid",
    "hex" : "0xF032"
  },
  {
    "name" : "FontAwesome5FreeSolid",
    "hex" : "0xF033"
  },
  {
    "name" : "FontAwesome5FreeSolid",
    "hex" : "0xF034"
  },
  {
    "name" : "FontAwesome5FreeSolid",
    "hex" : "0xF035"
  },
  {
    "name" : "FontAwesome5FreeSolid",
    "hex" : "0xF036"
  },
  {
    "name" : "FontAwesome5FreeSolid",
    "hex" : "0xF037"
  },
  {
    "name" : "FontAwesome5FreeSolid",
    "hex" : "0xF038"
  },
  {
    "name" : "FontAwesome5FreeSolid",
    "hex" : "0xF039"
  },
  {
    "name" : "FontAwesome5FreeSolid",
    "hex" : "0xF03A"
  },
  {
    "name" : "FontAwesome5FreeSolid",
    "hex" : "0xF03B"
  },
  {
    "name" : "FontAwesome5FreeSolid",
    "hex" : "0xF03C"
  },
  {
    "name" : "FontAwesome5FreeSolid",
    "hex" : "0xF03D"
  },
  {
    "name" : "FontAwesome5FreeSolid",
    "hex" : "0xF03E"
  },
  {
    "name" : "FontAwesome5FreeSolid",
    "hex" : "0xF041"
  },
  {
    "name" : "FontAwesome5FreeSolid",
    "hex" : "0xF042"
  },
  {
    "name" : "FontAwesome5FreeSolid",
    "hex" : "0xF043"
  },
  {
    "name" : "FontAwesome5FreeSolid",
    "hex" : "0xF044"
  },
  {
    "name" : "FontAwesome5FreeSolid",
    "hex" : "0xF048"
  },
  {
    "name" : "FontAwesome5FreeSolid",
    "hex" : "0xF049"
  },
  {
    "name" : "FontAwesome5FreeSolid",
    "hex" : "0xF04A"
  },
  {
    "name" : "FontAwesome5FreeSolid",
    "hex" : "0xF04B"
  },
  {
    "name" : "FontAwesome5FreeSolid",
    "hex" : "0xF04C"
  },
  {
    "name" : "FontAwesome5FreeSolid",
    "hex" : "0xF04D"
  },
  {
    "name" : "FontAwesome5FreeSolid",
    "hex" : "0xF04E"
  },
  {
    "name" : "FontAwesome5FreeSolid",
    "hex" : "0xF050"
  },
  {
    "name" : "FontAwesome5FreeSolid",
    "hex" : "0xF051"
  },
  {
    "name" : "FontAwesome5FreeSolid",
    "hex" : "0xF052"
  },
  {
    "name" : "FontAwesome5FreeSolid",
    "hex" : "0xF053"
  },
  {
    "name" : "FontAwesome5FreeSolid",
    "hex" : "0xF054"
  },
  {
    "name" : "FontAwesome5FreeSolid",
    "hex" : "0xF055"
  },
  {
    "name" : "FontAwesome5FreeSolid",
    "hex" : "0xF056"
  },
  {
    "name" : "FontAwesome5FreeSolid",
    "hex" : "0xF057"
  },
  {
    "name" : "FontAwesome5FreeSolid",
    "hex" : "0xF058"
  },
  {
    "name" : "FontAwesome5FreeSolid",
    "hex" : "0xF059"
  },
  {
    "name" : "FontAwesome5FreeSolid",
    "hex" : "0xF05A"
  },
  {
    "name" : "FontAwesome5FreeSolid",
    "hex" : "0xF05B"
  },
  {
    "name" : "FontAwesome5FreeSolid",
    "hex" : "0xF05E"
  },
  {
    "name" : "FontAwesome5FreeSolid",
    "hex" : "0xF060"
  },
  {
    "name" : "FontAwesome5FreeSolid",
    "hex" : "0xF061"
  },
  {
    "name" : "FontAwesome5FreeSolid",
    "hex" : "0xF062"
  },
  {
    "name" : "FontAwesome5FreeSolid",
    "hex" : "0xF063"
  },
  {
    "name" : "FontAwesome5FreeSolid",
    "hex" : "0xF064"
  },
  {
    "name" : "FontAwesome5FreeSolid",
    "hex" : "0xF065"
  },
  {
    "name" : "FontAwesome5FreeSolid",
    "hex" : "0xF066"
  },
  {
    "name" : "FontAwesome5FreeSolid",
    "hex" : "0xF067"
  },
  {
    "name" : "FontAwesome5FreeSolid",
    "hex" : "0xF068"
  },
  {
    "name" : "FontAwesome5FreeSolid",
    "hex" : "0xF069"
  },
  {
    "name" : "FontAwesome5FreeSolid",
    "hex" : "0xF06A"
  },
  {
    "name" : "FontAwesome5FreeSolid",
    "hex" : "0xF06B"
  },
  {
    "name" : "FontAwesome5FreeSolid",
    "hex" : "0xF06C"
  },
  {
    "name" : "FontAwesome5FreeSolid",
    "hex" : "0xF06D"
  },
  {
    "name" : "FontAwesome5FreeSolid",
    "hex" : "0xF06E"
  },
  {
    "name" : "FontAwesome5FreeSolid",
    "hex" : "0xF070"
  },
  {
    "name" : "FontAwesome5FreeSolid",
    "hex" : "0xF071"
  },
  {
    "name" : "FontAwesome5FreeSolid",
    "hex" : "0xF072"
  },
  {
    "name" : "FontAwesome5FreeSolid",
    "hex" : "0xF073"
  },
  {
    "name" : "FontAwesome5FreeSolid",
    "hex" : "0xF074"
  },
  {
    "name" : "FontAwesome5FreeSolid",
    "hex" : "0xF075"
  },
  {
    "name" : "FontAwesome5FreeSolid",
    "hex" : "0xF076"
  },
  {
    "name" : "FontAwesome5FreeSolid",
    "hex" : "0xF077"
  },
  {
    "name" : "FontAwesome5FreeSolid",
    "hex" : "0xF078"
  },
  {
    "name" : "FontAwesome5FreeSolid",
    "hex" : "0xF079"
  },
  {
    "name" : "FontAwesome5FreeSolid",
    "hex" : "0xF07A"
  },
  {
    "name" : "FontAwesome5FreeSolid",
    "hex" : "0xF07B"
  },
  {
    "name" : "FontAwesome5FreeSolid",
    "hex" : "0xF07C"
  },
  {
    "name" : "FontAwesome5FreeSolid",
    "hex" : "0xF080"
  },
  {
    "name" : "FontAwesome5FreeSolid",
    "hex" : "0xF083"
  },
  {
    "name" : "FontAwesome5FreeSolid",
    "hex" : "0xF084"
  },
  {
    "name" : "FontAwesome5FreeSolid",
    "hex" : "0xF085"
  },
  {
    "name" : "FontAwesome5FreeSolid",
    "hex" : "0xF086"
  },
  {
    "name" : "FontAwesome5FreeSolid",
    "hex" : "0xF089"
  },
  {
    "name" : "FontAwesome5FreeSolid",
    "hex" : "0xF08D"
  },
  {
    "name" : "FontAwesome5FreeSolid",
    "hex" : "0xF091"
  },
  {
    "name" : "FontAwesome5FreeSolid",
    "hex" : "0xF093"
  },
  {
    "name" : "FontAwesome5FreeSolid",
    "hex" : "0xF094"
  },
  {
    "name" : "FontAwesome5FreeSolid",
    "hex" : "0xF095"
  },
  {
    "name" : "FontAwesome5FreeSolid",
    "hex" : "0xF098"
  },
  {
    "name" : "FontAwesome5FreeSolid",
    "hex" : "0xF09C"
  },
  {
    "name" : "FontAwesome5FreeSolid",
    "hex" : "0xF09D"
  },
  {
    "name" : "FontAwesome5FreeSolid",
    "hex" : "0xF09E"
  },
  {
    "name" : "FontAwesome5FreeSolid",
    "hex" : "0xF0A0"
  },
  {
    "name" : "FontAwesome5FreeSolid",
    "hex" : "0xF0A1"
  },
  {
    "name" : "FontAwesome5FreeSolid",
    "hex" : "0xF0A3"
  },
  {
    "name" : "FontAwesome5FreeSolid",
    "hex" : "0xF0A4"
  },
  {
    "name" : "FontAwesome5FreeSolid",
    "hex" : "0xF0A5"
  },
  {
    "name" : "FontAwesome5FreeSolid",
    "hex" : "0xF0A6"
  },
  {
    "name" : "FontAwesome5FreeSolid",
    "hex" : "0xF0A7"
  },
  {
    "name" : "FontAwesome5FreeSolid",
    "hex" : "0xF0A8"
  },
  {
    "name" : "FontAwesome5FreeSolid",
    "hex" : "0xF0A9"
  },
  {
    "name" : "FontAwesome5FreeSolid",
    "hex" : "0xF0AA"
  },
  {
    "name" : "FontAwesome5FreeSolid",
    "hex" : "0xF0AB"
  },
  {
    "name" : "FontAwesome5FreeSolid",
    "hex" : "0xF0AC"
  },
  {
    "name" : "FontAwesome5FreeSolid",
    "hex" : "0xF0AD"
  },
  {
    "name" : "FontAwesome5FreeSolid",
    "hex" : "0xF0AE"
  },
  {
    "name" : "FontAwesome5FreeSolid",
    "hex" : "0xF0B0"
  },
  {
    "name" : "FontAwesome5FreeSolid",
    "hex" : "0xF0B1"
  },
  {
    "name" : "FontAwesome5FreeSolid",
    "hex" : "0xF0B2"
  },
  {
    "name" : "FontAwesome5FreeSolid",
    "hex" : "0xF0C0"
  },
  {
    "name" : "FontAwesome5FreeSolid",
    "hex" : "0xF0C1"
  },
  {
    "name" : "FontAwesome5FreeSolid",
    "hex" : "0xF0C2"
  },
  {
    "name" : "FontAwesome5FreeSolid",
    "hex" : "0xF0C3"
  },
  {
    "name" : "FontAwesome5FreeSolid",
    "hex" : "0xF0C4"
  },
  {
    "name" : "FontAwesome5FreeSolid",
    "hex" : "0xF0C5"
  },
  {
    "name" : "FontAwesome5FreeSolid",
    "hex" : "0xF0C6"
  },
  {
    "name" : "FontAwesome5FreeSolid",
    "hex" : "0xF0C7"
  },
  {
    "name" : "FontAwesome5FreeSolid",
    "hex" : "0xF0C8"
  },
  {
    "name" : "FontAwesome5FreeSolid",
    "hex" : "0xF0C9"
  },
  {
    "name" : "FontAwesome5FreeSolid",
    "hex" : "0xF0CA"
  },
  {
    "name" : "FontAwesome5FreeSolid",
    "hex" : "0xF0CB"
  },
  {
    "name" : "FontAwesome5FreeSolid",
    "hex" : "0xF0CC"
  },
  {
    "name" : "FontAwesome5FreeSolid",
    "hex" : "0xF0CD"
  },
  {
    "name" : "FontAwesome5FreeSolid",
    "hex" : "0xF0CE"
  },
  {
    "name" : "FontAwesome5FreeSolid",
    "hex" : "0xF0D0"
  },
  {
    "name" : "FontAwesome5FreeSolid",
    "hex" : "0xF0D1"
  },
  {
    "name" : "FontAwesome5FreeSolid",
    "hex" : "0xF0D7"
  },
  {
    "name" : "FontAwesome5FreeSolid",
    "hex" : "0xF0D8"
  },
  {
    "name" : "FontAwesome5FreeSolid",
    "hex" : "0xF0D9"
  },
  {
    "name" : "FontAwesome5FreeSolid",
    "hex" : "0xF0DA"
  },
  {
    "name" : "FontAwesome5FreeSolid",
    "hex" : "0xF0DB"
  },
  {
    "name" : "FontAwesome5FreeSolid",
    "hex" : "0xF0DC"
  },
  {
    "name" : "FontAwesome5FreeSolid",
    "hex" : "0xF0DD"
  },
  {
    "name" : "FontAwesome5FreeSolid",
    "hex" : "0xF0DE"
  },
  {
    "name" : "FontAwesome5FreeSolid",
    "hex" : "0xF0E0"
  },
  {
    "name" : "FontAwesome5FreeSolid",
    "hex" : "0xF0E2"
  },
  {
    "name" : "FontAwesome5FreeSolid",
    "hex" : "0xF0E3"
  },
  {
    "name" : "FontAwesome5FreeSolid",
    "hex" : "0xF0E7"
  },
  {
    "name" : "FontAwesome5FreeSolid",
    "hex" : "0xF0E8"
  },
  {
    "name" : "FontAwesome5FreeSolid",
    "hex" : "0xF0E9"
  },
  {
    "name" : "FontAwesome5FreeSolid",
    "hex" : "0xF0EA"
  },
  {
    "name" : "FontAwesome5FreeSolid",
    "hex" : "0xF0EB"
  },
  {
    "name" : "FontAwesome5FreeSolid",
    "hex" : "0xF0F0"
  },
  {
    "name" : "FontAwesome5FreeSolid",
    "hex" : "0xF0F1"
  },
  {
    "name" : "FontAwesome5FreeSolid",
    "hex" : "0xF0F2"
  },
  {
    "name" : "FontAwesome5FreeSolid",
    "hex" : "0xF0F3"
  },
  {
    "name" : "FontAwesome5FreeSolid",
    "hex" : "0xF0F4"
  },
  {
    "name" : "FontAwesome5FreeSolid",
    "hex" : "0xF0F8"
  },
  {
    "name" : "FontAwesome5FreeSolid",
    "hex" : "0xF0F9"
  },
  {
    "name" : "FontAwesome5FreeSolid",
    "hex" : "0xF0FA"
  },
  {
    "name" : "FontAwesome5FreeSolid",
    "hex" : "0xF0FB"
  },
  {
    "name" : "FontAwesome5FreeSolid",
    "hex" : "0xF0FC"
  },
  {
    "name" : "FontAwesome5FreeSolid",
    "hex" : "0xF0FD"
  },
  {
    "name" : "FontAwesome5FreeSolid",
    "hex" : "0xF0FE"
  },
  {
    "name" : "FontAwesome5FreeSolid",
    "hex" : "0xF100"
  },
  {
    "name" : "FontAwesome5FreeSolid",
    "hex" : "0xF101"
  },
  {
    "name" : "FontAwesome5FreeSolid",
    "hex" : "0xF102"
  },
  {
    "name" : "FontAwesome5FreeSolid",
    "hex" : "0xF103"
  },
  {
    "name" : "FontAwesome5FreeSolid",
    "hex" : "0xF104"
  },
  {
    "name" : "FontAwesome5FreeSolid",
    "hex" : "0xF105"
  },
  {
    "name" : "FontAwesome5FreeSolid",
    "hex" : "0xF106"
  },
  {
    "name" : "FontAwesome5FreeSolid",
    "hex" : "0xF107"
  },
  {
    "name" : "FontAwesome5FreeSolid",
    "hex" : "0xF108"
  },
  {
    "name" : "FontAwesome5FreeSolid",
    "hex" : "0xF109"
  },
  {
    "name" : "FontAwesome5FreeSolid",
    "hex" : "0xF10A"
  },
  {
    "name" : "FontAwesome5FreeSolid",
    "hex" : "0xF10B"
  },
  {
    "name" : "FontAwesome5FreeSolid",
    "hex" : "0xF10D"
  },
  {
    "name" : "FontAwesome5FreeSolid",
    "hex" : "0xF10E"
  },
  {
    "name" : "FontAwesome5FreeSolid",
    "hex" : "0xF110"
  },
  {
    "name" : "FontAwesome5FreeSolid",
    "hex" : "0xF111"
  },
  {
    "name" : "FontAwesome5FreeSolid",
    "hex" : "0xF118"
  },
  {
    "name" : "FontAwesome5FreeSolid",
    "hex" : "0xF119"
  },
  {
    "name" : "FontAwesome5FreeSolid",
    "hex" : "0xF11A"
  },
  {
    "name" : "FontAwesome5FreeSolid",
    "hex" : "0xF11B"
  },
  {
    "name" : "FontAwesome5FreeSolid",
    "hex" : "0xF11C"
  },
  {
    "name" : "FontAwesome5FreeSolid",
    "hex" : "0xF11E"
  },
  {
    "name" : "FontAwesome5FreeSolid",
    "hex" : "0xF120"
  },
  {
    "name" : "FontAwesome5FreeSolid",
    "hex" : "0xF121"
  },
  {
    "name" : "FontAwesome5FreeSolid",
    "hex" : "0xF122"
  },
  {
    "name" : "FontAwesome5FreeSolid",
    "hex" : "0xF124"
  },
  {
    "name" : "FontAwesome5FreeSolid",
    "hex" : "0xF125"
  },
  {
    "name" : "FontAwesome5FreeSolid",
    "hex" : "0xF126"
  },
  {
    "name" : "FontAwesome5FreeSolid",
    "hex" : "0xF127"
  },
  {
    "name" : "FontAwesome5FreeSolid",
    "hex" : "0xF128"
  },
  {
    "name" : "FontAwesome5FreeSolid",
    "hex" : "0xF129"
  },
  {
    "name" : "FontAwesome5FreeSolid",
    "hex" : "0xF12A"
  },
  {
    "name" : "FontAwesome5FreeSolid",
    "hex" : "0xF12B"
  },
  {
    "name" : "FontAwesome5FreeSolid",
    "hex" : "0xF12C"
  },
  {
    "name" : "FontAwesome5FreeSolid",
    "hex" : "0xF12D"
  },
  {
    "name" : "FontAwesome5FreeSolid",
    "hex" : "0xF12E"
  },
  {
    "name" : "FontAwesome5FreeSolid",
    "hex" : "0xF130"
  },
  {
    "name" : "FontAwesome5FreeSolid",
    "hex" : "0xF131"
  },
  {
    "name" : "FontAwesome5FreeSolid",
    "hex" : "0xF133"
  },
  {
    "name" : "FontAwesome5FreeSolid",
    "hex" : "0xF134"
  },
  {
    "name" : "FontAwesome5FreeSolid",
    "hex" : "0xF135"
  },
  {
    "name" : "FontAwesome5FreeSolid",
    "hex" : "0xF137"
  },
  {
    "name" : "FontAwesome5FreeSolid",
    "hex" : "0xF138"
  },
  {
    "name" : "FontAwesome5FreeSolid",
    "hex" : "0xF139"
  },
  {
    "name" : "FontAwesome5FreeSolid",
    "hex" : "0xF13A"
  },
  {
    "name" : "FontAwesome5FreeSolid",
    "hex" : "0xF13D"
  },
  {
    "name" : "FontAwesome5FreeSolid",
    "hex" : "0xF13E"
  },
  {
    "name" : "FontAwesome5FreeSolid",
    "hex" : "0xF140"
  },
  {
    "name" : "FontAwesome5FreeSolid",
    "hex" : "0xF141"
  },
  {
    "name" : "FontAwesome5FreeSolid",
    "hex" : "0xF142"
  },
  {
    "name" : "FontAwesome5FreeSolid",
    "hex" : "0xF143"
  },
  {
    "name" : "FontAwesome5FreeSolid",
    "hex" : "0xF144"
  },
  {
    "name" : "FontAwesome5FreeSolid",
    "hex" : "0xF146"
  },
  {
    "name" : "FontAwesome5FreeSolid",
    "hex" : "0xF14A"
  },
  {
    "name" : "FontAwesome5FreeSolid",
    "hex" : "0xF14B"
  },
  {
    "name" : "FontAwesome5FreeSolid",
    "hex" : "0xF14D"
  },
  {
    "name" : "FontAwesome5FreeSolid",
    "hex" : "0xF14E"
  },
  {
    "name" : "FontAwesome5FreeSolid",
    "hex" : "0xF150"
  },
  {
    "name" : "FontAwesome5FreeSolid",
    "hex" : "0xF151"
  },
  {
    "name" : "FontAwesome5FreeSolid",
    "hex" : "0xF152"
  },
  {
    "name" : "FontAwesome5FreeSolid",
    "hex" : "0xF153"
  },
  {
    "name" : "FontAwesome5FreeSolid",
    "hex" : "0xF154"
  },
  {
    "name" : "FontAwesome5FreeSolid",
    "hex" : "0xF155"
  },
  {
    "name" : "FontAwesome5FreeSolid",
    "hex" : "0xF156"
  },
  {
    "name" : "FontAwesome5FreeSolid",
    "hex" : "0xF157"
  },
  {
    "name" : "FontAwesome5FreeSolid",
    "hex" : "0xF158"
  },
  {
    "name" : "FontAwesome5FreeSolid",
    "hex" : "0xF159"
  },
  {
    "name" : "FontAwesome5FreeSolid",
    "hex" : "0xF15B"
  },
  {
    "name" : "FontAwesome5FreeSolid",
    "hex" : "0xF15C"
  },
  {
    "name" : "FontAwesome5FreeSolid",
    "hex" : "0xF15D"
  },
  {
    "name" : "FontAwesome5FreeSolid",
    "hex" : "0xF15E"
  },
  {
    "name" : "FontAwesome5FreeSolid",
    "hex" : "0xF162"
  },
  {
    "name" : "FontAwesome5FreeSolid",
    "hex" : "0xF163"
  },
  {
    "name" : "FontAwesome5FreeSolid",
    "hex" : "0xF164"
  },
  {
    "name" : "FontAwesome5FreeSolid",
    "hex" : "0xF165"
  },
  {
    "name" : "FontAwesome5FreeSolid",
    "hex" : "0xF182"
  },
  {
    "name" : "FontAwesome5FreeSolid",
    "hex" : "0xF183"
  },
  {
    "name" : "FontAwesome5FreeSolid",
    "hex" : "0xF185"
  },
  {
    "name" : "FontAwesome5FreeSolid",
    "hex" : "0xF186"
  },
  {
    "name" : "FontAwesome5FreeSolid",
    "hex" : "0xF187"
  },
  {
    "name" : "FontAwesome5FreeSolid",
    "hex" : "0xF188"
  },
  {
    "name" : "FontAwesome5FreeSolid",
    "hex" : "0xF191"
  },
  {
    "name" : "FontAwesome5FreeSolid",
    "hex" : "0xF192"
  },
  {
    "name" : "FontAwesome5FreeSolid",
    "hex" : "0xF193"
  },
  {
    "name" : "FontAwesome5FreeSolid",
    "hex" : "0xF195"
  },
  {
    "name" : "FontAwesome5FreeSolid",
    "hex" : "0xF197"
  },
  {
    "name" : "FontAwesome5FreeSolid",
    "hex" : "0xF199"
  },
  {
    "name" : "FontAwesome5FreeSolid",
    "hex" : "0xF19C"
  },
  {
    "name" : "FontAwesome5FreeSolid",
    "hex" : "0xF19D"
  },
  {
    "name" : "FontAwesome5FreeSolid",
    "hex" : "0xF1AB"
  },
  {
    "name" : "FontAwesome5FreeSolid",
    "hex" : "0xF1AC"
  },
  {
    "name" : "FontAwesome5FreeSolid",
    "hex" : "0xF1AD"
  },
  {
    "name" : "FontAwesome5FreeSolid",
    "hex" : "0xF1AE"
  },
  {
    "name" : "FontAwesome5FreeSolid",
    "hex" : "0xF1B0"
  },
  {
    "name" : "FontAwesome5FreeSolid",
    "hex" : "0xF1B2"
  },
  {
    "name" : "FontAwesome5FreeSolid",
    "hex" : "0xF1B3"
  },
  {
    "name" : "FontAwesome5FreeSolid",
    "hex" : "0xF1B8"
  },
  {
    "name" : "FontAwesome5FreeSolid",
    "hex" : "0xF1B9"
  },
  {
    "name" : "FontAwesome5FreeSolid",
    "hex" : "0xF1BA"
  },
  {
    "name" : "FontAwesome5FreeSolid",
    "hex" : "0xF1BB"
  },
  {
    "name" : "FontAwesome5FreeSolid",
    "hex" : "0xF1C0"
  },
  {
    "name" : "FontAwesome5FreeSolid",
    "hex" : "0xF1C1"
  },
  {
    "name" : "FontAwesome5FreeSolid",
    "hex" : "0xF1C2"
  },
  {
    "name" : "FontAwesome5FreeSolid",
    "hex" : "0xF1C3"
  },
  {
    "name" : "FontAwesome5FreeSolid",
    "hex" : "0xF1C4"
  },
  {
    "name" : "FontAwesome5FreeSolid",
    "hex" : "0xF1C5"
  },
  {
    "name" : "FontAwesome5FreeSolid",
    "hex" : "0xF1C6"
  },
  {
    "name" : "FontAwesome5FreeSolid",
    "hex" : "0xF1C7"
  },
  {
    "name" : "FontAwesome5FreeSolid",
    "hex" : "0xF1C8"
  },
  {
    "name" : "FontAwesome5FreeSolid",
    "hex" : "0xF1C9"
  },
  {
    "name" : "FontAwesome5FreeSolid",
    "hex" : "0xF1CD"
  },
  {
    "name" : "FontAwesome5FreeSolid",
    "hex" : "0xF1CE"
  },
  {
    "name" : "FontAwesome5FreeSolid",
    "hex" : "0xF1D8"
  },
  {
    "name" : "FontAwesome5FreeSolid",
    "hex" : "0xF1DA"
  },
  {
    "name" : "FontAwesome5FreeSolid",
    "hex" : "0xF1DC"
  },
  {
    "name" : "FontAwesome5FreeSolid",
    "hex" : "0xF1DD"
  },
  {
    "name" : "FontAwesome5FreeSolid",
    "hex" : "0xF1DE"
  },
  {
    "name" : "FontAwesome5FreeSolid",
    "hex" : "0xF1E0"
  },
  {
    "name" : "FontAwesome5FreeSolid",
    "hex" : "0xF1E1"
  },
  {
    "name" : "FontAwesome5FreeSolid",
    "hex" : "0xF1E2"
  },
  {
    "name" : "FontAwesome5FreeSolid",
    "hex" : "0xF1E3"
  },
  {
    "name" : "FontAwesome5FreeSolid",
    "hex" : "0xF1E4"
  },
  {
    "name" : "FontAwesome5FreeSolid",
    "hex" : "0xF1E5"
  },
  {
    "name" : "FontAwesome5FreeSolid",
    "hex" : "0xF1E6"
  },
  {
    "name" : "FontAwesome5FreeSolid",
    "hex" : "0xF1EA"
  },
  {
    "name" : "FontAwesome5FreeSolid",
    "hex" : "0xF1EB"
  },
  {
    "name" : "FontAwesome5FreeSolid",
    "hex" : "0xF1EC"
  },
  {
    "name" : "FontAwesome5FreeSolid",
    "hex" : "0xF1F6"
  },
  {
    "name" : "FontAwesome5FreeSolid",
    "hex" : "0xF1F8"
  },
  {
    "name" : "FontAwesome5FreeSolid",
    "hex" : "0xF1F9"
  },
  {
    "name" : "FontAwesome5FreeSolid",
    "hex" : "0xF1FA"
  },
  {
    "name" : "FontAwesome5FreeSolid",
    "hex" : "0xF1FB"
  },
  {
    "name" : "FontAwesome5FreeSolid",
    "hex" : "0xF1FC"
  },
  {
    "name" : "FontAwesome5FreeSolid",
    "hex" : "0xF1FD"
  },
  {
    "name" : "FontAwesome5FreeSolid",
    "hex" : "0xF1FE"
  },
  {
    "name" : "FontAwesome5FreeSolid",
    "hex" : "0xF200"
  },
  {
    "name" : "FontAwesome5FreeSolid",
    "hex" : "0xF201"
  },
  {
    "name" : "FontAwesome5FreeSolid",
    "hex" : "0xF204"
  },
  {
    "name" : "FontAwesome5FreeSolid",
    "hex" : "0xF205"
  },
  {
    "name" : "FontAwesome5FreeSolid",
    "hex" : "0xF206"
  },
  {
    "name" : "FontAwesome5FreeSolid",
    "hex" : "0xF207"
  },
  {
    "name" : "FontAwesome5FreeSolid",
    "hex" : "0xF20A"
  },
  {
    "name" : "FontAwesome5FreeSolid",
    "hex" : "0xF20B"
  },
  {
    "name" : "FontAwesome5FreeSolid",
    "hex" : "0xF217"
  },
  {
    "name" : "FontAwesome5FreeSolid",
    "hex" : "0xF218"
  },
  {
    "name" : "FontAwesome5FreeSolid",
    "hex" : "0xF21A"
  },
  {
    "name" : "FontAwesome5FreeSolid",
    "hex" : "0xF21B"
  },
  {
    "name" : "FontAwesome5FreeSolid",
    "hex" : "0xF21C"
  },
  {
    "name" : "FontAwesome5FreeSolid",
    "hex" : "0xF21D"
  },
  {
    "name" : "FontAwesome5FreeSolid",
    "hex" : "0xF21E"
  },
  {
    "name" : "FontAwesome5FreeSolid",
    "hex" : "0xF221"
  },
  {
    "name" : "FontAwesome5FreeSolid",
    "hex" : "0xF222"
  },
  {
    "name" : "FontAwesome5FreeSolid",
    "hex" : "0xF223"
  },
  {
    "name" : "FontAwesome5FreeSolid",
    "hex" : "0xF224"
  },
  {
    "name" : "FontAwesome5FreeSolid",
    "hex" : "0xF225"
  },
  {
    "name" : "FontAwesome5FreeSolid",
    "hex" : "0xF226"
  },
  {
    "name" : "FontAwesome5FreeSolid",
    "hex" : "0xF227"
  },
  {
    "name" : "FontAwesome5FreeSolid",
    "hex" : "0xF228"
  },
  {
    "name" : "FontAwesome5FreeSolid",
    "hex" : "0xF229"
  },
  {
    "name" : "FontAwesome5FreeSolid",
    "hex" : "0xF22A"
  },
  {
    "name" : "FontAwesome5FreeSolid",
    "hex" : "0xF22B"
  },
  {
    "name" : "FontAwesome5FreeSolid",
    "hex" : "0xF22C"
  },
  {
    "name" : "FontAwesome5FreeSolid",
    "hex" : "0xF22D"
  },
  {
    "name" : "FontAwesome5FreeSolid",
    "hex" : "0xF233"
  },
  {
    "name" : "FontAwesome5FreeSolid",
    "hex" : "0xF234"
  },
  {
    "name" : "FontAwesome5FreeSolid",
    "hex" : "0xF235"
  },
  {
    "name" : "FontAwesome5FreeSolid",
    "hex" : "0xF236"
  },
  {
    "name" : "FontAwesome5FreeSolid",
    "hex" : "0xF238"
  },
  {
    "name" : "FontAwesome5FreeSolid",
    "hex" : "0xF239"
  },
  {
    "name" : "FontAwesome5FreeSolid",
    "hex" : "0xF240"
  },
  {
    "name" : "FontAwesome5FreeSolid",
    "hex" : "0xF241"
  },
  {
    "name" : "FontAwesome5FreeSolid",
    "hex" : "0xF242"
  },
  {
    "name" : "FontAwesome5FreeSolid",
    "hex" : "0xF243"
  },
  {
    "name" : "FontAwesome5FreeSolid",
    "hex" : "0xF244"
  },
  {
    "name" : "FontAwesome5FreeSolid",
    "hex" : "0xF245"
  },
  {
    "name" : "FontAwesome5FreeSolid",
    "hex" : "0xF246"
  },
  {
    "name" : "FontAwesome5FreeSolid",
    "hex" : "0xF247"
  },
  {
    "name" : "FontAwesome5FreeSolid",
    "hex" : "0xF248"
  },
  {
    "name" : "FontAwesome5FreeSolid",
    "hex" : "0xF249"
  },
  {
    "name" : "FontAwesome5FreeSolid",
    "hex" : "0xF24D"
  },
  {
    "name" : "FontAwesome5FreeSolid",
    "hex" : "0xF24E"
  },
  {
    "name" : "FontAwesome5FreeSolid",
    "hex" : "0xF251"
  },
  {
    "name" : "FontAwesome5FreeSolid",
    "hex" : "0xF252"
  },
  {
    "name" : "FontAwesome5FreeSolid",
    "hex" : "0xF253"
  },
  {
    "name" : "FontAwesome5FreeSolid",
    "hex" : "0xF254"
  },
  {
    "name" : "FontAwesome5FreeSolid",
    "hex" : "0xF255"
  },
  {
    "name" : "FontAwesome5FreeSolid",
    "hex" : "0xF256"
  },
  {
    "name" : "FontAwesome5FreeSolid",
    "hex" : "0xF257"
  },
  {
    "name" : "FontAwesome5FreeSolid",
    "hex" : "0xF258"
  },
  {
    "name" : "FontAwesome5FreeSolid",
    "hex" : "0xF259"
  },
  {
    "name" : "FontAwesome5FreeSolid",
    "hex" : "0xF25A"
  },
  {
    "name" : "FontAwesome5FreeSolid",
    "hex" : "0xF25B"
  },
  {
    "name" : "FontAwesome5FreeSolid",
    "hex" : "0xF25C"
  },
  {
    "name" : "FontAwesome5FreeSolid",
    "hex" : "0xF25D"
  },
  {
    "name" : "FontAwesome5FreeSolid",
    "hex" : "0xF26C"
  },
  {
    "name" : "FontAwesome5FreeSolid",
    "hex" : "0xF271"
  },
  {
    "name" : "FontAwesome5FreeSolid",
    "hex" : "0xF272"
  },
  {
    "name" : "FontAwesome5FreeSolid",
    "hex" : "0xF273"
  },
  {
    "name" : "FontAwesome5FreeSolid",
    "hex" : "0xF274"
  },
  {
    "name" : "FontAwesome5FreeSolid",
    "hex" : "0xF275"
  },
  {
    "name" : "FontAwesome5FreeSolid",
    "hex" : "0xF276"
  },
  {
    "name" : "FontAwesome5FreeSolid",
    "hex" : "0xF277"
  },
  {
    "name" : "FontAwesome5FreeSolid",
    "hex" : "0xF279"
  },
  {
    "name" : "FontAwesome5FreeSolid",
    "hex" : "0xF27A"
  },
  {
    "name" : "FontAwesome5FreeSolid",
    "hex" : "0xF28B"
  },
  {
    "name" : "FontAwesome5FreeSolid",
    "hex" : "0xF28D"
  },
  {
    "name" : "FontAwesome5FreeSolid",
    "hex" : "0xF290"
  },
  {
    "name" : "FontAwesome5FreeSolid",
    "hex" : "0xF291"
  },
  {
    "name" : "FontAwesome5FreeSolid",
    "hex" : "0xF292"
  },
  {
    "name" : "FontAwesome5FreeSolid",
    "hex" : "0xF295"
  },
  {
    "name" : "FontAwesome5FreeSolid",
    "hex" : "0xF29A"
  },
  {
    "name" : "FontAwesome5FreeSolid",
    "hex" : "0xF29D"
  },
  {
    "name" : "FontAwesome5FreeSolid",
    "hex" : "0xF29E"
  },
  {
    "name" : "FontAwesome5FreeSolid",
    "hex" : "0xF2A0"
  },
  {
    "name" : "FontAwesome5FreeSolid",
    "hex" : "0xF2A1"
  },
  {
    "name" : "FontAwesome5FreeSolid",
    "hex" : "0xF2A2"
  },
  {
    "name" : "FontAwesome5FreeSolid",
    "hex" : "0xF2A3"
  },
  {
    "name" : "FontAwesome5FreeSolid",
    "hex" : "0xF2A4"
  },
  {
    "name" : "FontAwesome5FreeSolid",
    "hex" : "0xF2A7"
  },
  {
    "name" : "FontAwesome5FreeSolid",
    "hex" : "0xF2A8"
  },
  {
    "name" : "FontAwesome5FreeSolid",
    "hex" : "0xF2B5"
  },
  {
    "name" : "FontAwesome5FreeSolid",
    "hex" : "0xF2B6"
  },
  {
    "name" : "FontAwesome5FreeSolid",
    "hex" : "0xF2B9"
  },
  {
    "name" : "FontAwesome5FreeSolid",
    "hex" : "0xF2BB"
  },
  {
    "name" : "FontAwesome5FreeSolid",
    "hex" : "0xF2BD"
  },
  {
    "name" : "FontAwesome5FreeSolid",
    "hex" : "0xF2C1"
  },
  {
    "name" : "FontAwesome5FreeSolid",
    "hex" : "0xF2C2"
  },
  {
    "name" : "FontAwesome5FreeSolid",
    "hex" : "0xF2C7"
  },
  {
    "name" : "FontAwesome5FreeSolid",
    "hex" : "0xF2C8"
  },
  {
    "name" : "FontAwesome5FreeSolid",
    "hex" : "0xF2C9"
  },
  {
    "name" : "FontAwesome5FreeSolid",
    "hex" : "0xF2CA"
  },
  {
    "name" : "FontAwesome5FreeSolid",
    "hex" : "0xF2CB"
  },
  {
    "name" : "FontAwesome5FreeSolid",
    "hex" : "0xF2CC"
  },
  {
    "name" : "FontAwesome5FreeSolid",
    "hex" : "0xF2CD"
  },
  {
    "name" : "FontAwesome5FreeSolid",
    "hex" : "0xF2CE"
  },
  {
    "name" : "FontAwesome5FreeSolid",
    "hex" : "0xF2D0"
  },
  {
    "name" : "FontAwesome5FreeSolid",
    "hex" : "0xF2D1"
  },
  {
    "name" : "FontAwesome5FreeSolid",
    "hex" : "0xF2D2"
  },
  {
    "name" : "FontAwesome5FreeSolid",
    "hex" : "0xF2DB"
  },
  {
    "name" : "FontAwesome5FreeSolid",
    "hex" : "0xF2DC"
  },
  {
    "name" : "FontAwesome5FreeSolid",
    "hex" : "0xF2E5"
  },
  {
    "name" : "FontAwesome5FreeSolid",
    "hex" : "0xF2E7"
  },
  {
    "name" : "FontAwesome5FreeSolid",
    "hex" : "0xF2EA"
  },
  {
    "name" : "FontAwesome5FreeSolid",
    "hex" : "0xF2ED"
  },
  {
    "name" : "FontAwesome5FreeSolid",
    "hex" : "0xF2F1"
  },
  {
    "name" : "FontAwesome5FreeSolid",
    "hex" : "0xF2F2"
  },
  {
    "name" : "FontAwesome5FreeSolid",
    "hex" : "0xF2F5"
  },
  {
    "name" : "FontAwesome5FreeSolid",
    "hex" : "0xF2F6"
  },
  {
    "name" : "FontAwesome5FreeSolid",
    "hex" : "0xF2F9"
  },
  {
    "name" : "FontAwesome5FreeSolid",
    "hex" : "0xF302"
  },
  {
    "name" : "FontAwesome5FreeSolid",
    "hex" : "0xF303"
  },
  {
    "name" : "FontAwesome5FreeSolid",
    "hex" : "0xF309"
  },
  {
    "name" : "FontAwesome5FreeSolid",
    "hex" : "0xF30A"
  },
  {
    "name" : "FontAwesome5FreeSolid",
    "hex" : "0xF30B"
  },
  {
    "name" : "FontAwesome5FreeSolid",
    "hex" : "0xF30C"
  },
  {
    "name" : "FontAwesome5FreeSolid",
    "hex" : "0xF31E"
  },
  {
    "name" : "FontAwesome5FreeSolid",
    "hex" : "0xF337"
  },
  {
    "name" : "FontAwesome5FreeSolid",
    "hex" : "0xF338"
  },
  {
    "name" : "FontAwesome5FreeSolid",
    "hex" : "0xF358"
  },
  {
    "name" : "FontAwesome5FreeSolid",
    "hex" : "0xF359"
  },
  {
    "name" : "FontAwesome5FreeSolid",
    "hex" : "0xF35A"
  },
  {
    "name" : "FontAwesome5FreeSolid",
    "hex" : "0xF35B"
  },
  {
    "name" : "FontAwesome5FreeSolid",
    "hex" : "0xF35D"
  },
  {
    "name" : "FontAwesome5FreeSolid",
    "hex" : "0xF360"
  },
  {
    "name" : "FontAwesome5FreeSolid",
    "hex" : "0xF362"
  },
  {
    "name" : "FontAwesome5FreeSolid",
    "hex" : "0xF381"
  },
  {
    "name" : "FontAwesome5FreeSolid",
    "hex" : "0xF382"
  },
  {
    "name" : "FontAwesome5FreeSolid",
    "hex" : "0xF3A5"
  },
  {
    "name" : "FontAwesome5FreeSolid",
    "hex" : "0xF3BE"
  },
  {
    "name" : "FontAwesome5FreeSolid",
    "hex" : "0xF3BF"
  },
  {
    "name" : "FontAwesome5FreeSolid",
    "hex" : "0xF3C1"
  },
  {
    "name" : "FontAwesome5FreeSolid",
    "hex" : "0xF3C5"
  },
  {
    "name" : "FontAwesome5FreeSolid",
    "hex" : "0xF3CD"
  },
  {
    "name" : "FontAwesome5FreeSolid",
    "hex" : "0xF3D1"
  },
  {
    "name" : "FontAwesome5FreeSolid",
    "hex" : "0xF3E5"
  },
  {
    "name" : "FontAwesome5FreeSolid",
    "hex" : "0xF3ED"
  },
  {
    "name" : "FontAwesome5FreeSolid",
    "hex" : "0xF3FA"
  },
  {
    "name" : "FontAwesome5FreeSolid",
    "hex" : "0xF3FD"
  },
  {
    "name" : "FontAwesome5FreeSolid",
    "hex" : "0xF3FF"
  }
]